panel_of_agents/__init__.py
panel_of_agents/agents.py
panel_of_agents/context.py
panel_of_agents/decorators.py
panel_of_agents/flag.py
panel_of_agents/moderator.py
panel_of_agents/transmitter.py
panel_of_agents/utils.py
panel_of_agents/types/__init__.py
panel_of_agents/types/agents.py
panel_of_agents/types/context.py
panel_of_agents/types/flag.py
panel_of_agents/types/transmitter.py
panel_of_agents-0.1.0.dist-info/METADATA
panel_of_agents-0.1.0.dist-info/WHEEL
panel_of_agents-0.1.0.dist-info/licenses/LICENSE
panel_of_agents-0.1.0.dist-info/RECORD
