Metadata-Version: 2.4
Name: panel-of-agents
Version: 0.1.0
Summary: A framework for orchestrating multiple AI agents in collaborative discussions and tasks
Project-URL: Homepage, https://github.com/LighthouseAI-saas/PanelOfAgents
Project-URL: Repository, https://github.com/LighthouseAI-saas/PanelOfAgents
Author-email: Mohammed Ali <splitwireml@gmail.com>
Maintainer-email: Mohammed Ali <splitwireml@gmail.com>
License-Expression: AGPL-3.0
License-File: LICENSE
Keywords: agents,ai,automation,llms
Classifier: Development Status :: 3 - Alpha
Classifier: Intended Audience :: Developers
Classifier: Intended Audience :: Science/Research
Classifier: License :: OSI Approved :: GNU Affero General Public License v3
Classifier: Operating System :: OS Independent
Classifier: Programming Language :: Python
Classifier: Programming Language :: Python :: 3
Classifier: Programming Language :: Python :: 3.10
Classifier: Programming Language :: Python :: 3.11
Classifier: Programming Language :: Python :: 3.12
Classifier: Topic :: Scientific/Engineering :: Artificial Intelligence
Classifier: Topic :: Software Development :: Libraries :: Application Frameworks
Classifier: Topic :: Software Development :: Libraries :: Python Modules
Classifier: Typing :: Typed
Requires-Python: >=3.10
Requires-Dist: langchain
Requires-Dist: langchain-core
Requires-Dist: pydantic
Requires-Dist: pydantic-core
